import_logger.py
import_logger-1.0.0.dist-info/WHEEL
import_logger-1.0.0.dist-info/METADATA
import_logger-1.0.0.dist-info/RECORD
